ignf_gpf_api/Errors.py
ignf_gpf_api/__init__.py
ignf_gpf_api/__main__.py
ignf_gpf_api/py.typed
ignf_gpf_api/_conf/default.ini
ignf_gpf_api/_conf/json_schemas/upload_descriptor_file.json
ignf_gpf_api/_conf/json_schemas/workflow.json
ignf_gpf_api/_data/datasets/1_dataset_vector/CANTON.md5
ignf_gpf_api/_data/datasets/1_dataset_vector/CANTON_style.sld
ignf_gpf_api/_data/datasets/1_dataset_vector/upload_descriptor.json
ignf_gpf_api/_data/datasets/1_dataset_vector/CANTON/CANTON.cpg
ignf_gpf_api/_data/datasets/1_dataset_vector/CANTON/CANTON.dbf
ignf_gpf_api/_data/datasets/1_dataset_vector/CANTON/CANTON.prj
ignf_gpf_api/_data/datasets/1_dataset_vector/CANTON/CANTON.shp
ignf_gpf_api/_data/datasets/1_dataset_vector/CANTON/CANTON.shx
ignf_gpf_api/_data/datasets/2_dataset_archive/CANTON.md5
ignf_gpf_api/_data/datasets/2_dataset_archive/upload_descriptor.json
ignf_gpf_api/_data/datasets/2_dataset_archive/CANTON/CANTON.zip
ignf_gpf_api/_data/datasets/5_dataset_maj_bd_gpf/installation.sld
ignf_gpf_api/_data/datasets/5_dataset_maj_bd_gpf/upload_descriptor.json
ignf_gpf_api/_data/datasets/5_dataset_maj_bd_gpf/lot_1/installation-init.sql
ignf_gpf_api/_data/datasets/5_dataset_maj_bd_gpf/lot_2/installation.gpkg
ignf_gpf_api/_data/datasets/5_dataset_maj_bd_gpf/lot_3/installation.csv
ignf_gpf_api/_data/datasets/5_dataset_maj_bd_gpf/lot_3/installation.csvt
ignf_gpf_api/_data/workflows/generic_archive.jsonc
ignf_gpf_api/_data/workflows/generic_joincache.jsonc
ignf_gpf_api/_data/workflows/generic_maj_bdd.jsonc
ignf_gpf_api/_data/workflows/generic_moissonnage.jsonc
ignf_gpf_api/_data/workflows/generic_raster.jsonc
ignf_gpf_api/_data/workflows/generic_vecteur.jsonc
ignf_gpf_api/auth/Authentifier.py
ignf_gpf_api/auth/Errors.py
ignf_gpf_api/auth/Token.py
ignf_gpf_api/auth/__init__.py
ignf_gpf_api/helper/FileHelper.py
ignf_gpf_api/helper/JsonHelper.py
ignf_gpf_api/helper/PrintLogHelper.py
ignf_gpf_api/helper/__init__.py
ignf_gpf_api/io/ApiRequester.py
ignf_gpf_api/io/Color.py
ignf_gpf_api-0.1.10.dist-info/entry_points.txt
ignf_gpf_api-0.1.10.dist-info/LICENSE
ignf_gpf_api-0.1.10.dist-info/WHEEL
ignf_gpf_api-0.1.10.dist-info/METADATA
ignf_gpf_api-0.1.10.dist-info/RECORD
